{"flows": [{"isPermanent": true, "selector": {"criteria": [{"type": "IN_PORT", "port": 3}, {"mac": "56:8F:C2:71:C5:02", "type": "ETH_SRC", "port": 0}, {"mac": "32:4C:66:09:42:7E", "type": "ETH_DST", "port": 0}]}, "priority": 230, "deviceId": "of:0000000000000002", "timeout": 600, "treatment": {"instructions": [{"type": "OUTPUT", "port": 1}]}}, {"isPermanent": true, "selector": {"criteria": [{"type": "IN_PORT", "port": 1}, {"mac": "56:8F:C2:71:C5:02", "type": "ETH_SRC", "port": 0}, {"mac": "32:4C:66:09:42:7E", "type": "ETH_DST", "port": 0}]}, "priority": 230, "deviceId": "of:0000000000000001", "timeout": 600, "treatment": {"instructions": [{"type": "OUTPUT", "port": 2}]}}, {"isPermanent": true, "selector": {"criteria": [{"type": "IN_PORT", "port": 1}, {"mac": "56:8F:C2:71:C5:02", "type": "ETH_SRC", "port": 0}, {"mac": "32:4C:66:09:42:7E", "type": "ETH_DST", "port": 0}]}, "priority": 230, "deviceId": "of:0000000000000003", "timeout": 600, "treatment": {"instructions": [{"type": "OUTPUT", "port": 3}]}}, {"isPermanent": true, "selector": {"criteria": [{"type": "IN_PORT", "port": 3}, {"mac": "32:4C:66:09:42:7E", "type": "ETH_SRC", "port": 0}, {"mac": "56:8F:C2:71:C5:02", "type": "ETH_DST", "port": 0}]}, "priority": 230, "deviceId": "of:0000000000000003", "timeout": 600, "treatment": {"instructions": [{"type": "OUTPUT", "port": 1}]}}, {"isPermanent": true, "selector": {"criteria": [{"type": "IN_PORT", "port": 2}, {"mac": "32:4C:66:09:42:7E", "type": "ETH_SRC", "port": 0}, {"mac": "56:8F:C2:71:C5:02", "type": "ETH_DST", "port": 0}]}, "priority": 230, "deviceId": "of:0000000000000001", "timeout": 600, "treatment": {"instructions": [{"type": "OUTPUT", "port": 1}]}}, {"isPermanent": true, "selector": {"criteria": [{"type": "IN_PORT", "port": 1}, {"mac": "32:4C:66:09:42:7E", "type": "ETH_SRC", "port": 0}, {"mac": "56:8F:C2:71:C5:02", "type": "ETH_DST", "port": 0}]}, "priority": 230, "deviceId": "of:0000000000000002", "timeout": 600, "treatment": {"instructions": [{"type": "OUTPUT", "port": 3}]}}]}